open_edison/__init__.py
src/__init__.py
src/__main__.py
src/cli.py
src/config.py
src/config.pyi
src/events.py
src/gui.py
src/mcp_stdio_capture.py
src/oauth_manager.py
src/oauth_override.py
src/permissions.py
src/server.py
src/single_user_mcp.py
src/telemetry.py
src/vulture_whitelist.py
src/MySQLdb/__init__.py
src/demos/trifecta.py
src/frontend_dist/index.html
src/frontend_dist/sw.js
src/frontend_dist/assets/index-CbautcB1.css
src/frontend_dist/assets/index-DZe6R889.js
src/langgraph_integration/__init__.py
src/langgraph_integration/edison.py
src/langgraph_integration/tracking_api.py
src/mcp_importer/__init__.py
src/mcp_importer/__main__.py
src/mcp_importer/api.py
src/mcp_importer/cli.py
src/mcp_importer/export_cli.py
src/mcp_importer/exporters.py
src/mcp_importer/import_api.py
src/mcp_importer/importers.py
src/mcp_importer/merge.py
src/mcp_importer/parsers.py
src/mcp_importer/paths.py
src/mcp_importer/quick_cli.py
src/mcp_importer/types.py
src/mcp_importer/wizard_server.py
src/middleware/data_access_tracker.py
src/middleware/openai_mcp_session_id_patch.py
src/middleware/session_tracking.py
src/pysqlite2/__init__.py
src/setup_tui/__init__.py
src/setup_tui/main.py
src/tools/io.py
desktop_ext/INSTALLATION.md
desktop_ext/README.md
desktop_ext/build.sh
desktop_ext/icon.svg
desktop_ext/manifest.json
desktop_ext/open-edison-connector.dxt
desktop_ext/package.json
desktop_ext/test_connection.js
open_edison-0.1.133.dist-info/METADATA
open_edison-0.1.133.dist-info/WHEEL
open_edison-0.1.133.dist-info/entry_points.txt
open_edison-0.1.133.dist-info/licenses/LICENSE
open_edison-0.1.133.dist-info/RECORD
