Metadata-Version: 2.4
Name: open-edison
Version: 0.1.133
Summary: Open-source MCP security, aggregation, and monitoring. Single-user, self-hosted MCP proxy.
Author-email: Hugo Berg <hugo@edison.watch>
License-File: LICENSE
Requires-Python: <3.14,>=3.12
Requires-Dist: aiohttp>=3.12.14
Requires-Dist: aiosqlite>=0.20.0
Requires-Dist: beautifulsoup4>=4.13.5
Requires-Dist: fastapi>=0.116.1
Requires-Dist: fastmcp==2.11.3
Requires-Dist: hatchling>=1.27.0
Requires-Dist: httpx>=0.28.1
Requires-Dist: langchain-core>=0.3.76
Requires-Dist: langchain-openai>=0.3.33
Requires-Dist: langgraph>=0.6.7
Requires-Dist: loguru>=0.7.3
Requires-Dist: opentelemetry-api>=1.36.0
Requires-Dist: opentelemetry-exporter-otlp>=1.36.0
Requires-Dist: opentelemetry-sdk>=1.36.0
Requires-Dist: pyinstaller>=6.16.0
Requires-Dist: python-dotenv>=1.0.1
Requires-Dist: python-rapidjson>=1.21
Requires-Dist: pyyaml>=6.0.2
Requires-Dist: questionary>=2.1.1
Requires-Dist: sqlalchemy>=2.0.41
Requires-Dist: starlette>=0.47.1
Requires-Dist: uvicorn>=0.35.0
